aind_metadata_manager/__init__.py
aind_metadata_manager/metadata_manager.py
aind_metadata_manager-0.0.6.dist-info/licenses/LICENSE
aind_metadata_manager-0.0.6.dist-info/METADATA
aind_metadata_manager-0.0.6.dist-info/WHEEL
aind_metadata_manager-0.0.6.dist-info/top_level.txt
aind_metadata_manager-0.0.6.dist-info/RECORD
